<?xml version="1.0" encoding="UTF-8" standalone="no" ?><Mpeg7 xmlns="http://www.mpeg7.org/2001/MPEG-7_Schema" xmlns:xsi="http://www.w3.org/2000/10/XMLSchema-instance"><DescriptionUnit xsi:type="DescriptorCollectionType"><Descriptor NumberOfBitplanesDiscarded="0" numOfCoeff="256" xsi:type="ScalableColorType"><Coeff>-40 67 -96 27 5 39 33 29 31 -16 8 22 -33 0 23 22 7 -2 -2 2 3 17 -13 0 15 -2 -2 0 9 1 -7 -4 0 3 3 6 2 0 1 2 1 5 6 14 10 2 4 5 3 -2 -1 -1 0 3 3 0 0 -4 -2 -2 -7 0 -3 -3 0 0 1 0 0 0 0 1 1 1 2 6 4 2 2 1 0 -1 1 2 0 0 1 1 2 1 1 5 10 3 2 0 -3 -3 -1 -2 1 0 2 2 2 0 1 1 9 3 1 0 -7 -3 -2 -1 -1 0 1 0 1 -3 0 0 1 0 -1 1 0 0 0 0 0 0 0 0 0 0 1 0 0 0 0 0 0 0 2 -2 0 0 1 -1 0 0 2 -2 -2 0 1 0 0 0 -1 0 -1 0 0 0 0 1 0 -2 -1 0 0 -1 0 1 1 -4 -2 0 1 -2 0 2 0 -7 -3 0 1 -1 3 -1 0 0 -1 0 0 0 1 -1 -1 -2 -2 0 1 -1 0 1 -1 -1 -1 1 1 -2 0 3 -1 0 -3 1 0 -1 3 -1 0 0 -1 0 0 -1 0 1 0 0 0 0 0 -1 0 1 -1 0 0 1 0 -1 0 0 0 0 0 1 0 1 </Coeff></Descriptor><Descriptor xsi:type="DominantColorType"><SpatialCoherency>0</SpatialCoherency><Value><Percentage>3</Percentage><Index>1 10 15 </Index></Value><Value><Percentage>9</Percentage><Index>19 19 16 </Index></Value><Value><Percentage>11</Percentage><Index>28 28 25 </Index></Value><Value><Percentage>2</Percentage><Index>2 8 5 </Index></Value><Value><Percentage>1</Percentage><Index>16 22 7 </Index></Value><Value><Percentage>3</Percentage><Index>3 12 6 </Index></Value></Descriptor><Descriptor xsi:type="ColorLayoutType"><YDCCoeff>41</YDCCoeff><CbDCCoeff>22</CbDCCoeff><CrDCCoeff>24</CrDCCoeff><YACCoeff5>26 8 22 19 27 </YACCoeff5><CbACCoeff2>18 19 </CbACCoeff2><CrACCoeff2>14 12 </CrACCoeff2></Descriptor><Descriptor colorQuant="4" xsi:type="ColorStructureType"><Values>0 0 0 0 1 0 0 0 0 0 0 0 0 0 0 0 0 0 0 0 0 0 0 0 0 0 0 0 0 0 0 0 0 0 0 0 0 0 0 0 0 0 0 0 0 0 0 0 0 0 0 0 6 0 1 0 74 42 38 0 0 2 1 0 53 13 4 0 89 14 0 0 42 2 0 0 0 0 0 0 0 0 0 0 0 0 0 0 0 0 0 0 0 0 0 0 0 0 0 0 0 0 0 0 0 0 0 0 0 0 0 0 0 0 0 0 50 4 9 10 78 59 48 22 24 22 17 0 64 46 25 9 61 38 51 67 34 67 111 115 0 0 0 0 0 0 0 0 0 0 0 0 0 0 0 0 0 0 0 0 0 0 0 0 0 0 0 0 0 0 0 0 0 0 0 0 0 0 0 0 23 59 68 55 28 66 64 46 39 57 35 11 1 4 10 17 19 15 33 34 0 0 0 0 0 0 0 0 0 0 0 0 0 0 0 0 0 1 9 17 19 18 36 26 0 0 0 0 0 0 0 0 0 0 0 0 0 1 2 3 2 5 4 2 1 0 1 1 0 1 1 1 2 0 0 0 </Values></Descriptor><Descriptor xsi:type="HomogeneousTextureType"><Average>229</Average><StandardDeviation>21</StandardDeviation><Energy>160 212 215 176 214 215 147 177 176 161 181 174 122 147 133 157 125 134 92 98 107 127 113 78 76 47 56 100 67 35 </Energy><EnergyDeviation>158 216 217 171 217 217 136 176 175 154 174 170 109 142 118 142 109 131 83 80 102 108 111 76 68 33 40 91 48 29 </EnergyDeviation></Descriptor><Descriptor xsi:type="EdgeHistogramType"><BinCounts>0 0 0 0 0 2 3 2 3 2 1 2 1 3 3 0 0 0 0 1 0 0 0 0 1 1 0 5 4 3 3 1 2 6 3 2 3 4 2 3 0 1 1 1 3 2 1 2 4 4 4 2 6 5 3 0 0 2 0 0 0 0 0 0 0 2 1 2 1 2 0 0 0 1 2 0 0 0 0 0 </BinCounts></Descriptor><Descriptor xsi:type="ContourShapeType"><GlobalCurvature>2 2 </GlobalCurvature><HighestPeakY>0</HighestPeakY></Descriptor><Descriptor xsi:type="RegionShapeType"><MagnitudeOfART>15 15 9 11 13 15 13 14 5 5 9 15 13 2 11 10 6 13 12 7 8 8 5 10 5 2 5 5 5 10 10 7 11 6 5 </MagnitudeOfART></Descriptor></DescriptionUnit></Mpeg7>