<?xml version="1.0" encoding="UTF-8" standalone="no" ?><Mpeg7 xmlns="http://www.mpeg7.org/2001/MPEG-7_Schema" xmlns:xsi="http://www.w3.org/2000/10/XMLSchema-instance"><DescriptionUnit xsi:type="DescriptorCollectionType"><Descriptor NumberOfBitplanesDiscarded="0" numOfCoeff="256" xsi:type="ScalableColorType"><Coeff>-142 -4 -48 54 -8 14 22 29 31 13 11 22 -46 14 19 22 -6 1 0 2 -3 5 0 0 -15 2 2 0 -3 5 1 -4 3 3 0 1 0 0 1 2 1 1 1 3 1 2 4 5 -2 -3 2 2 2 3 3 0 0 0 0 -2 1 0 -3 -3 1 0 0 0 0 0 0 1 0 1 2 1 2 2 2 1 3 1 0 1 0 0 1 1 1 1 2 1 3 3 2 0 -3 -1 0 1 0 0 2 2 2 2 2 1 3 3 1 0 -7 -3 0 1 0 0 1 0 1 1 1 0 1 0 -1 1 0 0 0 0 0 0 0 0 1 0 0 0 0 0 0 0 1 0 0 -1 0 0 1 -1 0 0 0 0 0 0 1 0 3 -1 0 0 0 0 0 0 3 -1 0 -1 0 0 0 -1 1 0 0 -1 0 0 1 -2 0 0 0 0 0 0 1 -1 3 -1 0 0 0 0 0 0 3 -1 0 -1 0 0 1 -1 0 0 1 -1 0 1 1 -2 0 0 0 0 0 1 0 -1 3 -1 1 0 0 0 0 -1 1 0 1 0 0 0 0 -1 0 0 0 0 0 1 0 -1 0 0 0 0 0 1 0 1 </Coeff></Descriptor><Descriptor xsi:type="DominantColorType"><SpatialCoherency>0</SpatialCoherency><Value><Percentage>9</Percentage><Index>16 15 12 </Index></Value><Value><Percentage>22</Percentage><Index>24 22 21 </Index></Value></Descriptor><Descriptor xsi:type="ColorLayoutType"><YDCCoeff>47</YDCCoeff><CbDCCoeff>22</CbDCCoeff><CrDCCoeff>38</CrDCCoeff><YACCoeff5>22 21 21 13 20 </YACCoeff5><CbACCoeff2>16 16 </CbACCoeff2><CrACCoeff2>17 16 </CrACCoeff2></Descriptor><Descriptor colorQuant="4" xsi:type="ColorStructureType"><Values>0 0 0 0 0 0 0 0 0 0 0 0 0 0 0 0 0 0 0 0 0 0 0 0 0 0 0 0 0 0 0 0 0 0 0 0 0 0 0 0 0 0 0 0 0 0 0 0 0 0 0 0 0 0 0 0 0 0 0 0 0 0 0 0 0 0 0 0 0 2 3 2 0 0 0 0 0 0 0 0 0 0 0 0 0 0 0 0 0 0 0 0 0 0 0 0 0 0 0 0 0 0 0 0 0 0 0 0 0 0 0 0 0 0 0 0 0 0 0 0 0 0 0 0 0 0 0 0 0 5 26 23 46 117 183 149 16 65 67 19 0 0 0 0 0 0 0 0 0 0 0 0 0 0 0 0 0 0 0 0 0 0 0 0 0 0 0 0 0 0 0 0 0 0 0 0 0 0 0 0 0 0 1 0 0 0 0 0 0 0 0 0 0 1 1 0 0 9 16 12 0 0 0 0 0 0 0 0 0 0 0 0 0 0 0 0 0 0 0 0 0 0 1 4 0 0 0 0 0 0 0 0 0 0 0 0 0 0 0 0 0 0 0 0 0 0 0 0 0 0 0 0 1 0 4 6 </Values></Descriptor><Descriptor xsi:type="HomogeneousTextureType"><Average>199</Average><StandardDeviation>3</StandardDeviation><Energy>153 204 205 159 203 206 139 171 171 137 168 166 115 136 117 123 110 124 85 81 78 94 75 66 67 29 20 58 20 19 </Energy><EnergyDeviation>151 208 207 156 207 209 128 169 172 131 162 163 104 133 104 112 99 122 77 67 76 81 71 64 59 19 13 51 12 14 </EnergyDeviation></Descriptor><Descriptor xsi:type="EdgeHistogramType"><BinCounts>0 0 0 0 0 0 3 4 0 3 0 2 0 4 1 0 1 5 0 0 2 0 1 0 0 5 1 6 2 6 4 2 3 6 5 0 0 6 0 0 1 0 1 1 1 3 2 3 7 6 1 3 6 4 5 1 3 4 1 0 2 0 0 1 0 1 4 3 7 1 4 2 6 2 3 1 1 4 2 0 </BinCounts></Descriptor><Descriptor xsi:type="ContourShapeType"><GlobalCurvature>2 2 </GlobalCurvature><HighestPeakY>0</HighestPeakY></Descriptor><Descriptor xsi:type="RegionShapeType"><MagnitudeOfART>13 15 8 9 10 15 14 2 12 8 6 13 11 1 8 7 3 9 9 8 2 3 4 7 3 2 6 4 4 9 7 5 6 4 2 </MagnitudeOfART></Descriptor></DescriptionUnit></Mpeg7>