<?xml version="1.0" encoding="UTF-8" standalone="no" ?><Mpeg7 xmlns="http://www.mpeg7.org/2001/MPEG-7_Schema" xmlns:xsi="http://www.w3.org/2000/10/XMLSchema-instance"><DescriptionUnit xsi:type="DescriptorCollectionType"><Descriptor NumberOfBitplanesDiscarded="0" numOfCoeff="256" xsi:type="ScalableColorType"><Coeff>-161 15 -29 54 -12 14 22 29 22 13 11 22 -27 14 19 22 6 1 0 2 -1 5 0 0 -15 2 2 0 -3 5 1 -4 3 3 0 1 0 0 1 2 1 1 1 3 1 2 4 5 2 -3 2 2 2 3 3 0 0 0 0 -2 1 0 -3 -3 0 1 0 0 0 0 0 1 1 1 2 1 2 2 2 1 -3 -1 0 1 0 0 1 1 2 1 2 1 3 3 2 0 -3 -3 0 1 0 0 2 2 2 2 2 1 3 3 1 0 -7 -2 0 1 0 0 1 0 1 1 1 0 1 0 -1 1 0 0 0 0 0 0 0 0 0 1 0 0 0 0 0 0 0 0 0 -1 0 0 1 -1 0 0 0 0 0 0 1 0 3 -1 0 0 0 0 0 0 1 0 0 -1 0 0 0 -1 0 0 0 -1 0 0 1 -2 0 0 0 0 0 0 1 -1 3 -1 0 0 0 0 0 0 0 0 0 -1 0 0 1 -1 0 0 1 -1 0 1 1 -2 0 0 0 0 0 1 0 -1 3 -1 1 0 0 0 0 -1 0 0 1 0 0 0 0 -1 0 0 0 0 0 1 0 -1 0 0 0 0 0 1 0 1 </Coeff></Descriptor><Descriptor xsi:type="DominantColorType"><SpatialCoherency>0</SpatialCoherency><Value><Percentage>0</Percentage><Index>7 7 5 </Index></Value><Value><Percentage>17</Percentage><Index>28 27 25 </Index></Value><Value><Percentage>10</Percentage><Index>21 20 19 </Index></Value><Value><Percentage>3</Percentage><Index>15 14 13 </Index></Value></Descriptor><Descriptor xsi:type="ColorLayoutType"><YDCCoeff>52</YDCCoeff><CbDCCoeff>24</CbDCCoeff><CrDCCoeff>36</CrDCCoeff><YACCoeff5>19 25 15 13 21 </YACCoeff5><CbACCoeff2>16 16 </CbACCoeff2><CrACCoeff2>17 17 </CrACCoeff2></Descriptor><Descriptor colorQuant="4" xsi:type="ColorStructureType"><Values>0 0 0 0 0 0 0 0 0 0 0 0 0 0 0 0 0 0 0 0 0 0 0 0 0 0 0 0 0 0 0 0 0 0 0 0 0 0 0 0 0 0 0 0 0 0 0 0 0 0 0 0 0 0 0 0 0 0 0 0 0 0 0 0 0 0 0 0 0 1 0 0 0 0 0 0 0 0 0 0 0 0 0 0 0 0 0 0 0 0 0 0 0 0 0 0 0 0 0 0 0 0 0 0 0 0 0 0 0 0 0 0 0 0 0 0 0 0 0 0 0 0 0 0 0 0 0 0 0 0 0 1 7 85 146 172 13 31 42 8 0 0 0 0 0 0 0 0 0 0 0 0 0 0 0 0 0 0 0 0 0 0 0 0 0 0 0 0 0 0 0 0 0 0 0 0 0 0 0 0 0 4 0 0 9 1 0 0 0 0 0 0 8 26 37 40 47 41 58 54 0 0 0 0 0 0 0 0 0 0 0 0 0 0 0 0 16 30 30 19 10 6 1 0 0 0 0 0 0 0 0 0 0 0 0 0 0 0 0 0 0 0 0 0 0 0 0 0 0 0 0 0 0 0 0 0 </Values></Descriptor><Descriptor xsi:type="HomogeneousTextureType"><Average>216</Average><StandardDeviation>1</StandardDeviation><Energy>156 207 209 162 207 210 142 174 174 140 173 171 119 140 122 126 118 131 90 87 83 98 83 74 73 38 28 64 29 28 </Energy><EnergyDeviation>154 211 211 159 211 213 130 173 175 134 166 168 107 136 108 114 106 128 81 73 81 86 80 72 65 27 20 58 19 23 </EnergyDeviation></Descriptor><Descriptor xsi:type="EdgeHistogramType"><BinCounts>0 0 0 0 0 0 0 0 0 0 0 0 0 0 0 0 0 0 0 0 0 0 0 0 0 0 3 2 0 2 0 4 0 2 2 0 0 0 1 1 2 0 4 1 2 0 3 3 0 4 1 1 3 3 5 2 2 3 6 2 4 0 1 1 1 1 5 3 3 5 2 3 4 2 5 3 0 2 6 2 </BinCounts></Descriptor><Descriptor xsi:type="ContourShapeType"><GlobalCurvature>2 2 </GlobalCurvature><HighestPeakY>0</HighestPeakY></Descriptor><Descriptor xsi:type="RegionShapeType"><MagnitudeOfART>11 15 1 1 6 15 14 7 9 5 4 13 10 4 2 1 1 12 11 8 4 4 3 0 1 1 3 2 1 8 7 6 3 2 3 </MagnitudeOfART></Descriptor></DescriptionUnit></Mpeg7>