<?xml version="1.0" encoding="UTF-8" standalone="no" ?><Mpeg7 xmlns="http://www.mpeg7.org/2001/MPEG-7_Schema" xmlns:xsi="http://www.w3.org/2000/10/XMLSchema-instance"><DescriptionUnit xsi:type="DescriptorCollectionType"><Descriptor NumberOfBitplanesDiscarded="0" numOfCoeff="256" xsi:type="ScalableColorType"><Coeff>-82 22 0 6 -7 12 20 29 25 25 31 25 -31 0 -30 19 3 1 0 2 -5 5 0 0 -3 10 15 1 -4 5 1 -4 3 3 1 2 1 1 1 2 5 1 1 3 1 2 4 5 0 -3 -1 -3 2 4 4 0 -1 0 0 -2 1 0 -3 -3 0 0 0 0 0 0 0 1 1 1 2 1 2 2 2 1 -2 -1 -1 0 -1 -1 1 1 -2 1 2 1 3 3 2 0 -3 -3 -3 -7 -3 -3 2 1 1 2 2 1 3 3 1 0 -3 -3 0 -2 -3 -7 0 -1 1 1 1 0 1 0 -1 1 0 0 0 0 0 0 0 0 0 0 0 0 0 0 0 0 0 0 0 -1 0 0 1 -1 0 0 0 0 0 0 1 0 1 1 -1 -1 1 -1 0 0 3 0 0 -1 0 0 0 -1 3 0 0 -1 0 0 1 -2 0 0 0 0 0 0 1 -1 0 1 -3 -3 1 -3 0 1 3 -1 0 -1 0 0 1 -1 1 0 1 -1 0 1 1 -2 0 0 0 0 0 1 0 -1 -1 -1 1 -3 3 -3 -1 0 3 0 1 0 0 0 0 -1 0 0 0 0 0 1 0 -1 0 0 0 0 0 1 0 1 </Coeff></Descriptor><Descriptor xsi:type="DominantColorType"><SpatialCoherency>0</SpatialCoherency><Value><Percentage>10</Percentage><Index>17 17 17 </Index></Value><Value><Percentage>20</Percentage><Index>24 24 25 </Index></Value><Value><Percentage>0</Percentage><Index>13 11 7 </Index></Value><Value><Percentage>0</Percentage><Index>25 22 16 </Index></Value></Descriptor><Descriptor xsi:type="ColorLayoutType"><YDCCoeff>49</YDCCoeff><CbDCCoeff>33</CbDCCoeff><CrDCCoeff>31</CrDCCoeff><YACCoeff5>24 13 21 19 16 </YACCoeff5><CbACCoeff2>16 14 </CbACCoeff2><CrACCoeff2>16 17 </CrACCoeff2></Descriptor><Descriptor colorQuant="4" xsi:type="ColorStructureType"><Values>0 0 0 0 0 0 0 0 0 0 0 0 0 0 0 0 0 0 0 0 0 0 0 0 0 0 0 0 0 0 0 0 0 0 0 0 0 0 0 0 0 0 0 0 0 0 0 0 0 0 0 0 0 0 0 0 0 0 0 0 0 0 0 0 0 0 0 0 7 18 17 11 0 0 0 0 0 0 0 0 0 0 0 0 0 0 0 0 0 0 0 0 0 0 0 0 0 0 0 0 0 0 0 0 0 0 0 0 0 0 0 0 0 0 0 0 0 0 0 0 0 0 0 0 0 0 0 0 0 9 0 0 14 30 9 1 0 5 4 0 0 0 0 0 0 0 0 0 0 0 0 0 0 0 0 0 0 0 0 0 0 0 0 0 0 0 0 0 0 0 0 0 0 0 0 0 0 0 0 0 0 1 0 0 0 0 0 0 0 0 2 2 0 5 12 48 67 109 117 68 0 0 0 0 1 2 2 1 0 0 0 0 0 0 0 0 0 0 4 51 69 48 12 1 0 0 0 0 0 0 0 1 2 3 8 12 16 29 38 43 47 51 59 71 70 64 64 57 53 43 23 11 4 1 0 0 </Values></Descriptor><Descriptor xsi:type="HomogeneousTextureType"><Average>220</Average><StandardDeviation>30</StandardDeviation><Energy>173 216 216 170 205 211 165 179 173 145 169 170 136 176 126 129 116 131 106 127 93 104 84 74 94 87 38 73 34 37 </Energy><EnergyDeviation>168 219 218 167 209 214 155 173 172 141 163 166 121 170 111 115 105 128 93 106 88 88 80 72 83 77 26 63 23 31 </EnergyDeviation></Descriptor><Descriptor xsi:type="EdgeHistogramType"><BinCounts>0 0 0 0 0 2 2 1 0 4 0 6 4 2 2 3 3 5 4 3 1 5 3 0 3 1 3 4 4 1 1 4 3 3 2 1 3 4 1 3 0 5 2 0 0 0 1 0 0 1 0 2 2 0 2 0 1 0 0 0 0 0 0 0 0 0 0 0 0 0 0 0 0 0 0 0 0 0 0 0 </BinCounts></Descriptor><Descriptor xsi:type="ContourShapeType"><GlobalCurvature>2 2 </GlobalCurvature><HighestPeakY>0</HighestPeakY></Descriptor><Descriptor xsi:type="RegionShapeType"><MagnitudeOfART>6 15 1 1 5 14 13 4 10 5 8 14 12 2 8 4 3 13 12 6 8 4 5 7 3 2 6 1 5 10 8 6 7 4 3 </MagnitudeOfART></Descriptor></DescriptionUnit></Mpeg7>